setup.py
Flask_Ticketing.egg-info/PKG-INFO
Flask_Ticketing.egg-info/SOURCES.txt
Flask_Ticketing.egg-info/dependency_links.txt
Flask_Ticketing.egg-info/top_level.txt
flask_ticketing/__init__.py
flask_ticketing/core.py
flask_ticketing/model.py