Metadata-Version: 1.0
Name: Flask-Ticketing
Version: 0.2
Summary: Ticketing extension for Flask
Home-page: https://github.com/gerelorant/Flask-Ticketing
Author: Gere Lóránt
Author-email: gerelorant@gmail.com
License: MIT
Platform: UNKNOWN
